[{"line":1,"elements":[{"start_timestamp":"2022-09-06T20:03:42.411Z","before":[{"result":{"duration":2969541300,"status":"passed"},"match":{"location":"StepDefinitions.StepDefinitions.BeforeEachTest()"}}],"line":11,"name":"Login to Site and Add an Item To Cart","description":"","id":"add-to-cart;login-to-site-and-add-an-item-to-cart;;2","after":[{"result":{"duration":447637500,"status":"passed"},"match":{"location":"StepDefinitions.StepDefinitions.AfterEachTest()"}}],"type":"scenario","keyword":"Scenario Outline","steps":[{"result":{"duration":649498200,"status":"passed"},"line":4,"name":"user navigates to the Login page","match":{"location":"StepDefinitions.StepDefinitions.navigate_to_the_login_page()"},"keyword":"Given "},{"result":{"duration":393955800,"status":"passed"},"line":5,"name":"user enters standard_user and secret_sauce","match":{"arguments":[{"val":"standard_user","offset":12},{"val":"secret_sauce","offset":30}],"location":"StepDefinitions.StepDefinitions.enter_username_and_password(java.lang.String,java.lang.String)"},"keyword":"And "},{"result":{"duration":229950300,"status":"passed"},"line":6,"name":"clicks the Login CTA","match":{"location":"StepDefinitions.StepDefinitions.click_login_CTA()"},"keyword":"And "},{"result":{"duration":177632100,"status":"passed"},"line":7,"name":"the user selects an item and adds it to the Cart","match":{"location":"StepDefinitions.StepDefinitions.select_item_and_add_it_to_cart()"},"keyword":"When "},{"result":{"duration":247654200,"status":"passed"},"line":8,"name":"the user verifies that the item is added to the card","match":{"location":"StepDefinitions.StepDefinitions.verify_item_is_added()"},"keyword":"Then "}]}],"name":"Add to Cart","description":"","id":"add-to-cart","keyword":"Feature","uri":"file:src/main/java/Features/addToCart.feature","tags":[]}]